snakeland/CHECKSUM-SHA3-256.py
snakeland/__init__.py
snakeland/__main__.py
snakeland/snakeland.py
snakeland-0.0.7.dist-info/LICENSE
snakeland-0.0.7.dist-info/METADATA
snakeland-0.0.7.dist-info/WHEEL
snakeland-0.0.7.dist-info/entry_points.txt
snakeland-0.0.7.dist-info/top_level.txt
snakeland-0.0.7.dist-info/RECORD
