Metadata-Version: 2.2
Name: snakeland
Version: 0.0.7
Summary: Instant Python3 script installer.
Author-email: MikeTurkey <voice@miketurkey.com>
Maintainer-email: MikeTurkey <voice@miketurkey.com>
License: ######################################################################
Classifier: Topic :: Software Development
Classifier: Environment :: Console
Classifier: Development Status :: 4 - Beta
Classifier: License :: OSI Approved :: GNU General Public License v3 (GPLv3)
Classifier: Operating System :: MacOS :: MacOS X
Classifier: Operating System :: POSIX :: BSD :: FreeBSD
Classifier: Programming Language :: Python :: 3 :: Only
Classifier: Programming Language :: Python :: 3.9
Classifier: Programming Language :: Python :: 3.10
Classifier: Programming Language :: Python :: 3.11
Requires-Python: <=4.0,>=3.9
License-File: LICENSE
Requires-Dist: requests
Requires-Dist: importlib-metadata; python_version < "3.8"
